MANIFEST.in
README.rst
setup.py
pybz/__init__.py
pybz/cmd.py
pybz/meta.py
pybz/rest.py
pybz.egg-info/PKG-INFO
pybz.egg-info/SOURCES.txt
pybz.egg-info/dependency_links.txt
pybz.egg-info/entry_points.txt
pybz.egg-info/requires.txt
pybz.egg-info/top_level.txt