Metadata-Version: 1.0
Name: pybz
Version: 0.1.5
Summary: Python Bugzilla Console Utility
Home-page: http://github.com/acornejo/pybz
Author: Alex Cornejo
Author-email: acornejo@gmail.com
License: GPL
Platform: all
